README.md
setup.py
khh/__init__.py
khh/khh.py
khh/khh_test.py
khh/pqueue.py
khh.egg-info/PKG-INFO
khh.egg-info/SOURCES.txt
khh.egg-info/dependency_links.txt
khh.egg-info/requires.txt
khh.egg-info/top_level.txt