Metadata-Version: 1.0
Name: khh
Version: 1.0.0
Summary: K- Heavy Hitters data-structure
Home-page: UNKNOWN
Author: Sam Wenke
Author-email: samwenke@gmail.com
License: BSD
Platform: any
